daves_dev_tools/__init__.py
daves_dev_tools/__main__.py
daves_dev_tools/clean.py
daves_dev_tools/distribute.py
daves_dev_tools/errors.py
daves_dev_tools/install_editable.py
daves_dev_tools/make_typed.py
daves_dev_tools/py.typed
daves_dev_tools/uninstall_all.py
daves_dev_tools/utilities.py
daves_dev_tools/git/__init__.py
daves_dev_tools/git/__main__.py
daves_dev_tools/git/download.py
daves_dev_tools/git/py.typed
daves_dev_tools/git/tag_version.py
daves_dev_tools/requirements/__init__.py
daves_dev_tools/requirements/__main__.py
daves_dev_tools/requirements/_utilities.py
daves_dev_tools/requirements/freeze.py
daves_dev_tools/requirements/py.typed
daves_dev_tools/requirements/update.py
daves_dev_tools/requirements/utilities.py
daves_dev_tools-2.1.4.dist-info/METADATA
daves_dev_tools-2.1.4.dist-info/WHEEL
daves_dev_tools-2.1.4.dist-info/entry_points.txt
daves_dev_tools-2.1.4.dist-info/top_level.txt
daves_dev_tools-2.1.4.dist-info/RECORD
