Metadata-Version: 2.1
Name: daves-dev-tools
Version: 2.1.4
Summary: Dave's developer tools
Home-page: https://github.com/enorganic/daves-dev-tools
Author-email: david@belais.me
License: MIT
Keywords: dave,dev,tools
Requires-Python: ~=3.8
Requires-Dist: packaging
Requires-Dist: pip
Requires-Dist: twine>=5.1
Requires-Dist: wheel
Requires-Dist: tomli~=2.0
Requires-Dist: tomli-w~=1.0
Requires-Dist: more-itertools<11.0,>=8.0
Requires-Dist: dependence~=0.3
